[
  {
    "id": "WORK_572fe7b3",
    "liber_number": null,
    "title": "Aleister Crowley Cocaine Magick Level Press",
    "class": "Unclassified",
    "date_composed": null,
    "location_composed": null,
    "summary": null,
    "document_id": "DOC_572fe7b3"
  },
  {
    "id": "WORK_760950bc",
    "liber_number": null,
    "title": "aleister crowley in england the return of the grea",
    "class": "Unclassified",
    "date_composed": null,
    "location_composed": null,
    "summary": null,
    "document_id": "DOC_760950bc"
  },
  {
    "id": "WORK_49044d78",
    "liber_number": null,
    "title": "aleister crowley in england the return of the grea",
    "class": "Unclassified",
    "date_composed": null,
    "location_composed": null,
    "summary": null,
    "document_id": "DOC_49044d78"
  },
  {
    "id": "WORK_afd6bc3e",
    "liber_number": null,
    "title": "Aleister Crowley Magic Theory and Practice",
    "class": "Unclassified",
    "date_composed": null,
    "location_composed": null,
    "summary": null,
    "document_id": "DOC_afd6bc3e"
  },
  {
    "id": "WORK_6b8a254d",
    "liber_number": null,
    "title": "aleister crowley magick, rock and roll, and the wi",
    "class": "Unclassified",
    "date_composed": null,
    "location_composed": null,
    "summary": null,
    "document_id": "DOC_6b8a254d"
  },
  {
    "id": "WORK_e81f0dbe",
    "liber_number": null,
    "title": "aleister crowley magick, rock and roll, and the wi",
    "class": "Unclassified",
    "date_composed": null,
    "location_composed": null,
    "summary": null,
    "document_id": "DOC_e81f0dbe"
  },
  {
    "id": "WORK_ac950a9b",
    "liber_number": null,
    "title": "Aleister Crowley The Master Therion Frieda Harris The Book of Thoth_ A Short Essay on the Tarot of the Egyptians Being the Equinox Volume III No V Samuel Weiser Inc",
    "class": "Unclassified",
    "date_composed": null,
    "location_composed": null,
    "summary": null,
    "document_id": "DOC_ac950a9b"
  },
  {
    "id": "WORK_e43fbee1",
    "liber_number": null,
    "title": "Aleister Crowley Victor B Neuburg Mary Desti The Vision and the Voice with Commentary and Other Papers Samuel Weiser",
    "class": "Unclassified",
    "date_composed": null,
    "location_composed": null,
    "summary": null,
    "document_id": "DOC_e43fbee1"
  },
  {
    "id": "WORK_bf69bd63",
    "liber_number": null,
    "title": "Jake Stratton Kent Aleister Crowley Liber Pyramidos Hadean Press",
    "class": "Unclassified",
    "date_composed": null,
    "location_composed": null,
    "summary": null,
    "document_id": "DOC_bf69bd63"
  },
  {
    "id": "WORK_d0b427ca",
    "liber_number": null,
    "title": "Keith Readdy One Truth and One Spirit_ Aleister Crowley s Spiritual Legacy Ibis Press",
    "class": "Unclassified",
    "date_composed": null,
    "location_composed": null,
    "summary": null,
    "document_id": "DOC_d0b427ca"
  },
  {
    "id": "WORK_40d4f39c",
    "liber_number": null,
    "title": "S L MacGregor Mathers_ Aleister Crowley_ Hymenaeus Beta The Goetia _ the lesser key of Solomon the King _ Lemegeton Book I Clavicula Salomonis Regis Samuel Weiser",
    "class": "Unclassified",
    "date_composed": null,
    "location_composed": null,
    "summary": null,
    "document_id": "DOC_40d4f39c"
  },
  {
    "id": "WORK_ee897869",
    "liber_number": null,
    "title": "Stephen Skinner Aleister Crowley s Four Books of Magick_ Liber ABA libgen li",
    "class": "Unclassified",
    "date_composed": null,
    "location_composed": null,
    "summary": null,
    "document_id": "DOC_ee897869"
  },
  {
    "id": "WORK_8901ea67",
    "liber_number": null,
    "title": "Tracey W Tupman Theatre Magick_ Aleister Crowley and the Rites of Eleusis The Ohio State University",
    "class": "Unclassified",
    "date_composed": null,
    "location_composed": null,
    "summary": null,
    "document_id": "DOC_8901ea67"
  }
]